grav_waldo/__init__.py
grav_waldo/evaltoolkit.py
grav_waldo/unet.py
grav_waldo/waldo.py
grav_waldo/wfdset.py
grav_waldo-0.1.0.dist-info/LICENSE
grav_waldo-0.1.0.dist-info/METADATA
grav_waldo-0.1.0.dist-info/WHEEL
grav_waldo-0.1.0.dist-info/top_level.txt
grav_waldo-0.1.0.dist-info/RECORD
